[
  {
    "ironManToys": [
      {
        "picture": "https://down-ph.img.susercontent.com/file/6d630a44fcc85b5d690861500f6b8b06",
        "name": "Iron Man gadgets",
        "price": "$33",
        "rating": 4.9,
        "sellerName": "Toy Universe",
        "sellerEmail": "info@toyuniverse.com",
        "quantity": 10,
        "description": "Explore the world of Iron Man with these incredible gadgets. Each gadget is meticulously designed to replicate Tony Stark's creations and provide endless fun for fans of all ages."
      },
      {
        "picture": "https://i.ebayimg.com/images/g/1fgAAOSw69hfkbBr/s-l1600.jpg",
        "name": "Iron Man Infinity War",
        "price": "$37",
        "rating": 5.0,
        "sellerName": "Marvel Merchandise",
        "sellerEmail": "sales@marvelmerch.com",
        "quantity": 5,
        "description": "Get ready for an epic battle with the Iron Man Infinity War figure. This highly detailed action figure features Iron Man in his iconic suit from the blockbuster movie, ready to take on any threat."
      }
    ]
  },
  {
    "spiderManToys": [
      {
        "picture": "https://ae01.alicdn.com/kf/He89048eb79d54967819760d8561c23ffV/The-Avengers-Spider-Man-Action-Figure-Infinity-War-Pvc-Model-Toys-Spiderman-Doll-Movable-Doll-Toys.jpg_640x640.jpg",
        "name": "Spider Man with spider plate",
        "price": "$24",
        "rating": 4.8,
        "sellerName": "Web-Slinging Toys",
        "sellerEmail": "sales@webslingingtoys.com",
        "quantity": 8,
        "description": "Join Spider-Man in his mission to protect the city with this action figure featuring a spider plate. With its movable joints and realistic details, this Spider Man figure is perfect for recreating your favorite scenes from the movies."
      },
      {
        "picture": "https://previews.123rf.com/images/aapsky/aapsky1711/aapsky171100163/90287020-a-number-of-spider-man-toys-russia-saint-petersburg-10-november-2017.jpg",
        "name": "Spider Man Gang",
        "price": "$55",
        "rating": 4.6,
        "sellerName": "Hero Haven",
        "sellerEmail": "contact@herohaven.com",
        "quantity": 3,
        "description": "Unleash the power of the Spider Man Gang with this set of action figures. Each figure showcases a different Spider-Man suit, allowing you to create your own epic battles and adventures."
      }
    ]
  },
  {
    "grootToys": [
      {
        "picture": "https://preview.redd.it/hucmya190r371.jpg?width=640&crop=smart&auto=webp&s=416ee1d7e63175953254b0713f0a9448ff4fb1ca",
        "name": "Groot team",
        "price": "$23",
        "rating": 4.8,
        "sellerName": "Galactic Toys",
        "sellerEmail": "info@galactictoys.com",
        "quantity": 12,
        "description": "Assemble your own Groot team with this set of adorable action figures. Each figure features Groot in a different pose and expression, capturing the lovable nature of this iconic character."
      },
      {
        "picture": "https://ae01.alicdn.com/kf/Hf243cb658a904c87bd1649010f74408e2/Hot-Toys-1-1-Marvel-Guardians-of-The-Galaxy-Groot-Avengers-Cute-Baby-Tree-Man-Joints.jpg_.webp",
        "name": "Mini groot",
        "price": "$25",
        "rating": 4.6,
        "sellerName": "Toy Galaxy",
        "sellerEmail": "sales@toygalaxy.com",
        "quantity": 7,
        "description": "Bring home the cutest member of the Guardians of the Galaxy with this mini Groot figure. With its movable joints and adorable design, this figure is a must-have for any Groot fan."
      }
    ]
  }
]